{
  "lesson": {
    "title": "Phương trình mặt cầu và tương giao",
    "title_vi": "Phương trình mặt cầu và tương giao",
    "level": "nhan_biet",
    "topic": "Phương trình và hình học Oxyz"
  },
  "theory": {
    "title": "Phương trình mặt cầu và tương giao",
    "title_vi": "Phương trình mặt cầu và tương giao",
    "content_md": "## 1. Công thức trọng tâm\n\n| Công thức | Dùng khi | Cần nhớ |\n|---|---|---|\n| $(x-a)^2+(y-b)^2+(z-c)^2=R^2$ | Biết tâm $I(a,b,c)$ và bán kính $R$ | Tâm là $I(a,b,c)$, cần $R>0$ |\n| $x^2+y^2+z^2+2ux+2vy+2wz+d=0$ | Đề cho dạng khai triển | Tâm $I(-u,-v,-w)$, $R^2=u^2+v^2+w^2-d$ |\n| $IM=R$ với $M(x,y,z)$ thuộc mặt cầu | Lập phương trình mặt cầu từ định nghĩa | Biến đổi về dạng chính tắc |\n| $d(I,(P))$ so với $R$ | Xét tương giao mặt cầu và mặt phẳng | $d<R$: cắt theo đường tròn; $d=R$: tiếp xúc; $d>R$: không giao |\n| $d(I,\\Delta)$ so với $R$ | Xét tương giao mặt cầu và đường thẳng | $d<R$: cắt tại 2 điểm; $d=R$: tiếp xúc; $d>R$: không giao |\n| $r=\\sqrt{R^2-d^2}$ | Tính bán kính đường tròn giao tuyến của mặt cầu và mặt phẳng | $d=d(I,(P))$ |\n\n## 2. Hiểu nhanh công thức\n\n- Mặt cầu là tập hợp các điểm $M(x,y,z)$ cách đều tâm $I(a,b,c)$ một khoảng không đổi $R$.\n- Dạng chính tắc cho ta đọc ngay tâm và bán kính. Đây là dạng nên ưu tiên đưa về khi làm bài.\n- Dạng khai triển thuận tiện khi đề cho phương trình tổng quát; chỉ cần nhóm hạng tử để tìm tâm và $R^2$.\n- Điều kiện quan trọng: $R^2>0$ thì mới là mặt cầu thực. Nếu $R^2=0$ thì chỉ còn một điểm, nếu $R^2<0$ thì không có mặt cầu.\n- Với tương giao, bản chất là so sánh khoảng cách từ tâm đến đối tượng đang xét với bán kính $R$.\n\n> [Hình minh họa: Vẽ hệ trục Oxyz, một mặt cầu tâm I, một mặt phẳng (P) cắt mặt cầu tạo đường tròn và một đường thẳng \\Delta lần lượt ở ba vị trí: cắt hai điểm, tiếp xúc, không cắt; học sinh cần quan sát việc so sánh khoảng cách từ I đến (P) hoặc \\Delta với bán kính R]\n\n## 3. Khi nào dùng?\n\n- Đề cho tâm và bán kính $\\Rightarrow$ viết ngay dạng chính tắc.\n- Đề cho phương trình có $x^2+y^2+z^2$ và các hạng tử bậc nhất $\\Rightarrow$ tìm tâm, bán kính từ dạng khai triển.\n- Đề hỏi mặt cầu cắt hay tiếp xúc mặt phẳng $\\Rightarrow$ tính $d(I,(P))$ rồi so với $R$.\n- Đề hỏi mặt cầu cắt hay tiếp xúc đường thẳng $\\Rightarrow$ tính $d(I,\\Delta)$ hoặc thế tham số đường thẳng vào phương trình mặt cầu.\n- Đề hỏi giao tuyến mặt cầu và mặt phẳng là đường tròn bán kính bao nhiêu $\\Rightarrow$ dùng $r=\\sqrt{R^2-d^2}$.\n- Đề hỏi số giao điểm với đường thẳng $\\Rightarrow$ ưu tiên so sánh $d(I,\\Delta)$ với $R$ để kết luận nhanh.\n\n## 4. Ví dụ mẫu\n\n**Ví dụ 1.** Viết phương trình mặt cầu tâm $I(1,-2,3)$, bán kính $R=4$.\n\nVì đề cho tâm và bán kính, ta dùng dạng chính tắc.\n\n1. Mặt cầu có dạng $$(x-a)^2+(y-b)^2+(z-c)^2=R^2.$$ \n2. Thay $a=1$, $b=-2$, $c=3$, $R=4$.\n3. Suy ra phương trình là $$ (x-1)^2+(y+2)^2+(z-3)^2=16. $$\n\n**Ví dụ 2.** Cho mặt cầu\n$$S: x^2+y^2+z^2-2x+4y-6z-2=0$$\nvà mặt phẳng $(P): x+y+z-1=0$. Xét tương giao của $S$ và $(P)$.\n\nVì đề cho phương trình khai triển và hỏi tương giao với mặt phẳng, ta tìm tâm, bán kính rồi so sánh $d(I,(P))$ với $R$.\n\n1. Từ $S$, có $u=-1$, $v=2$, $w=-3$, $d=-2$ nên tâm $I(1,-2,3)$.\n2. $$R^2=u^2+v^2+w^2-d=1+4+9+2=16 \\Rightarrow R=4.$$\n3. Khoảng cách từ $I$ đến $(P)$:\n$$d(I,(P))=\\frac{|1-2+3-1|}{\\sqrt{1^2+1^2+1^2}}=\\frac{1}{\\sqrt{3}}.$$ \n4. Vì $\\dfrac{1}{\\sqrt{3}}<4$, mặt phẳng cắt mặt cầu theo một đường tròn.\n5. Nếu cần bán kính đường tròn giao tuyến:\n$$r=\\sqrt{16-\\frac{1}{3}}=\\sqrt{\\frac{47}{3}}.$$\n\n**Nhận xét nhanh cho đường thẳng:** Nếu gặp đường thẳng $\\Delta$ trong Oxyz, hãy viết $\\Delta$ qua một điểm và một vectơ chỉ phương, rồi tính $d(I,\\Delta)$ để biết số giao điểm với mặt cầu.\n\n## 5. Lưu ý & lỗi sai\n\n- Sai: Nhìn dạng khai triển rồi kết luận tâm là $I(u,v,w)$.\n  Vì sao sai: Dấu của tọa độ tâm bị ngược.\n  Sửa: Với $x^2+y^2+z^2+2ux+2vy+2wz+d=0$, tâm là $I(-u,-v,-w)$.\n\n- Sai: Tính bán kính bằng $R=\\sqrt{d-u^2-v^2-w^2}$.\n  Vì sao sai: Dùng sai công thức, dễ ra số âm dưới căn.\n  Sửa: Dùng $R^2=u^2+v^2+w^2-d$.\n\n- Sai: Mặt phẳng cắt mặt cầu khi $d(I,(P))\\le R$.\n  Vì sao sai: Trường hợp bằng chỉ là tiếp xúc, không phải cắt theo đường tròn.\n  Sửa: Phân biệt rõ $d<R$, $d=R$, $d>R$.\n\n- Sai: Với đường thẳng, chỉ thế vào phương trình mặt cầu rồi kết luận vội khi chưa xét biệt thức.\n  Vì sao sai: Có thể bỏ sót trường hợp tiếp xúc hoặc hai giao điểm.\n  Sửa: Nên so sánh $d(I,\\Delta)$ với $R$ hoặc nếu thế tham số thì phải xét số nghiệm.\n\n- Sai: Không kiểm tra $R^2>0$.\n  Vì sao sai: Có phương trình nhìn giống mặt cầu nhưng không biểu diễn mặt cầu thực.\n  Sửa: Sau khi tìm $R^2$, luôn kiểm tra dấu.\n\n## 6. Chốt nhanh\n\n- Dạng chính tắc giúp đọc ngay tâm $I(a,b,c)$ và bán kính $R$.\n- Dạng khai triển: tâm $I(-u,-v,-w)$, $R^2=u^2+v^2+w^2-d$.\n- Tương giao với mặt phẳng: so sánh $d(I,(P))$ với $R$.\n- Tương giao với đường thẳng: so sánh $d(I,\\Delta)$ với $R$ hoặc thế tham số để xét số nghiệm.\n- Luôn kiểm tra điều kiện $R^2>0$ trước khi kết luận là mặt cầu.",
    "key_rules": [
      "Dạng chính tắc: $(x-a)^2+(y-b)^2+(z-c)^2=R^2$.",
      "Dạng khai triển: tâm $I(-u,-v,-w)$, $R^2=u^2+v^2+w^2-d$.",
      "So sánh khoảng cách từ tâm đến mặt phẳng hoặc đường thẳng với $R$ để xét tương giao.",
      "Mặt phẳng cắt mặt cầu theo đường tròn có bán kính $r=\\sqrt{R^2-d^2}$.",
      "Luôn kiểm tra $R^2>0$ trước khi kết luận."
    ],
    "common_mistakes": [
      "Sai: Tâm của $x^2+y^2+z^2+2ux+2vy+2wz+d=0$ là $I(u,v,w)$ -> Đúng: Tâm là $I(-u,-v,-w)$.",
      "Sai: Bán kính thỏa $R^2=d-u^2-v^2-w^2$ -> Đúng: $R^2=u^2+v^2+w^2-d$.",
      "Sai: $d(I,(P))=R$ thì mặt phẳng cắt mặt cầu theo đường tròn -> Đúng: Khi đó mặt phẳng tiếp xúc với mặt cầu.",
      "Sai: Không cần xét $R^2$ vì phương trình đã có đủ $x^2,y^2,z^2$ -> Đúng: Phải kiểm tra $R^2>0$ để là mặt cầu thực.",
      "Sai: Đường thẳng giao mặt cầu thì luôn có 2 điểm chung -> Đúng: Có thể có 2 điểm, 1 điểm tiếp xúc hoặc không có điểm chung tùy $d(I,\\Delta)$ và $R$."
    ]
  }
}